sincpro_logger/__init__.py
sincpro_logger/adapters/discord_hardware_notifier.py
sincpro_logger/adapters/hardware_collector.py
sincpro_logger/domain/hardware_info.py
sincpro_logger/logger.py
sincpro_logger/setup.py
sincpro_logger-0.1.0.dist-info/LICENSE.md
sincpro_logger-0.1.0.dist-info/METADATA
sincpro_logger-0.1.0.dist-info/WHEEL
sincpro_logger-0.1.0.dist-info/RECORD
