Metadata-Version: 2.3
Name: sincpro-logger
Version: 0.1.0
Summary: A logging module for sincpro applications
License: LICENSE.md
Author: Andres Gutierrez
Author-email: andru1236@gmail.com
Requires-Python: >=3.10,<4.0
Classifier: License :: Other/Proprietary License
Classifier: Programming Language :: Python :: 3
Classifier: Programming Language :: Python :: 3.10
Classifier: Programming Language :: Python :: 3.11
Classifier: Programming Language :: Python :: 3.12
Classifier: Programming Language :: Python :: 3.13
Requires-Dist: requests (>=2.31.0,<3.0.0)
Requires-Dist: structlog (>=25.2.0,<26.0.0)
